constrained_linear_regression/__init__.py
constrained_linear_regression/base.py
constrained_linear_regression/constrained_linear_regression.py
constrained_linear_regression/matrix_constrained_linear_regression.py
constrained_linear_regression/multi_constrained_linear_regression.py
constrained_linear_regression-0.0.5.dist-info/METADATA
constrained_linear_regression-0.0.5.dist-info/WHEEL
constrained_linear_regression-0.0.5.dist-info/top_level.txt
constrained_linear_regression-0.0.5.dist-info/RECORD
