Metadata-Version: 2.1
Name: constrained_linear_regression
Version: 0.0.5
Summary: Constrained linear regression in scikit-learn style
Home-page: https://github.com/avidale/constrained-linear-regression
Author: David Dale
Author-email: dale.david@mail.ru
License: MIT
Classifier: Development Status :: 3 - Alpha
Classifier: Programming Language :: Python :: 3
Classifier: License :: OSI Approved :: MIT License
Classifier: Operating System :: OS Independent
Requires-Dist: scikit-learn
Requires-Dist: numpy
